{
  "rails": "Ruby on Rails フレームワーク",
  "sinatra": "軽量 Web フレームワーク",
  "puma": "マルチスレッド Web サーバー",
  "rackup": "Rack アプリの起動ツール",
  "mysql2": "MySQL クライアント",
  "bcrypt": "パスワードのハッシュ化",
  "brakeman": "セキュリティ脆弱性スキャナー",
  "dotenv": "環境変数を .env から読み込む",
  "dotenv-rails": "環境変数を .env から読み込む（Rails）",
  "importmap-rails": "Import Maps による JS 管理",
  "stimulus-rails": "軽量 JavaScript フレームワーク（Stimulus）",
  "turbo-rails": "高速なページ遷移・フォーム送信（Turbo）",
  "sprockets-rails": "アセットパイプライン",
  "react_on_rails": "Rails と React を統合",
  "shakapacker": "Webpack 設定の Rails 向けラッパー",
  "jbuilder": "JSON レスポンスを DSL で構築",
  "view_component": "再利用可能なビューコンポーネント",
  "rswag": "RSpec から Swagger ドキュメントを生成",
  "sequel": "ORM / データベースツールキット",
  "nokogiri": "XML/HTML パーサー",
  "rack": "Ruby Web サーバーインターフェース",
  "rake": "Ruby のタスクランナー",
  "bootsnap": "起動時間の高速化",
  "ruby-lsp": "Ruby 言語サーバー",
  "web-console": "開発環境の Rails コンソール",
  "debug": "Ruby デバッガー",
  "sinatra-contrib": "Sinatra 拡張機能コレクション",
  "rubocop": "Ruby の静的解析・フォーマッター",
  "rubocop-rails-omakase": "Rails 公式の RuboCop プリセット",
  "rubocop-rspec": "RSpec 向け RuboCop ルール",
  "erb_lint": "ERB テンプレートの静的解析",
  "htmlbeautifier": "ERB テンプレートのフォーマット",
  "prettier": "コードフォーマッター",
  "rspec-rails": "Rails 向けテストフレームワーク",
  "rspec": "Ruby のテストフレームワーク",
  "factory_bot_rails": "テスト用フィクスチャファクトリー（Rails）",
  "factory_bot": "テスト用フィクスチャファクトリー",
  "faker": "テスト用ダミーデータ生成",
  "capybara": "E2E テストの DSL",
  "selenium-webdriver": "ブラウザ自動操作（E2E テスト）",
  "rack-test": "Rack アプリのテストヘルパー",
  "tzinfo-data": "タイムゾーンデータ（Windows 向け）"
}
